Metadata-Version: 2.1
Name: font-manager
Version: 0.1.0
Summary: Library for managing fonts in PyQt5 applications
Author: Андрей
Author-email: andrey960123@gmail.com
Classifier: Programming Language :: Python :: 3
Classifier: License :: OSI Approved :: MIT License
Classifier: Operating System :: OS Independent
Requires-Dist: PyQt5>=5.15.0
